dnnnlp/__init__.py
dnnnlp/exec.py
dnnnlp/layer.py
dnnnlp/model.py
dnnnlp/utils.py
dnnnlp-1.1.4.dist-info/LICENSE
dnnnlp-1.1.4.dist-info/METADATA
dnnnlp-1.1.4.dist-info/WHEEL
dnnnlp-1.1.4.dist-info/top_level.txt
dnnnlp-1.1.4.dist-info/RECORD
