Metadata-Version: 2.1
Name: dnnnlp
Version: 1.1.4
Summary: Deep Neural Networks for Natural Language Processing classification or sequential task written by PyTorch.
Home-page: https://github.com/NUSTM/pytorch-dnnnlp
Author: KzXuan
Author-email: kaizhouxuan@gmail.com
License: MIT
Platform: UNKNOWN
Classifier: License :: Free for non-commercial use
Classifier: Topic :: Scientific/Engineering :: Artificial Intelligence
Classifier: Programming Language :: Python :: 3.5
Classifier: Programming Language :: Python :: 3.5
Classifier: Programming Language :: Python :: 3.6
Classifier: Programming Language :: Python :: 3.7
Requires-Dist: numpy
Requires-Dist: scikit-learn (>=0.21.0)
Requires-Dist: torch (>=1.2.0)
Requires-Dist: torchcrf (>=0.7.2)
